{
  "type": "object",
  "properties": {
    "title": {
      "type": "string",
      "description": "Video title in Traditional Chinese only"
    },
    "brief_description": {
      "type": "string",
      "description": "Brief description of the video in Traditional Chinese only"
    },
    "middle_description": {
      "type": "string",
      "description": "Medium length description of the video in Traditional Chinese only"
    },
    "long_description": {
      "type": "string",
      "description": "Detailed description of the video in Traditional Chinese only"
    },
    "tags": {
      "type": "array",
      "items": {
        "type": "string",
        "description": "Traditional Chinese tag"
      },
      "description": "Array of tags related to the video content, Traditional Chinese only"
    },
    "english_words_to_learn": {
      "type": "array",
      "items": {
        "type": "object",
        "properties": {
          "word": {
            "type": "string",
            "description": "English word or phrase to learn"
          },
          "timestamp_range": {
            "type": "object",
            "properties": {
              "start": {
                "type": "string",
                "pattern": "^\\d{2}:\\d{2}:\\d{2},\\d{3}$",
                "description": "Start timestamp in HH:MM:SS,mmm format"
              },
              "end": {
                "type": "string",
                "pattern": "^\\d{2}:\\d{2}:\\d{2},\\d{3}$",
                "description": "End timestamp in HH:MM:SS,mmm format"
              }
            },
            "required": ["start", "end"],
            "additionalProperties": false
          }
        },
        "required": ["word", "timestamp_range"],
        "additionalProperties": false
      },
      "description": "English words with timestamps"
    },
    "teaser": {
      "type": "object",
      "properties": {
        "start": {
          "type": "string",
          "pattern": "^\\d{2}:\\d{2}:\\d{2},\\d{3}$",
          "description": "Teaser start timestamp in HH:MM:SS,mmm format"
        },
        "end": {
          "type": "string",
          "pattern": "^\\d{2}:\\d{2}:\\d{2},\\d{3}$",
          "description": "Teaser end timestamp in HH:MM:SS,mmm format"
        }
      },
      "required": ["start", "end"],
      "additionalProperties": false,
      "description": "Timestamp range for teaser"
    },
    "cover": {
      "type": "string",
      "pattern": "^\\d{2}:\\d{2}:\\d{2},\\d{3}$",
      "description": "Cover image timestamp in HH:MM:SS,mmm format"
    },
    "publish_category": {
      "type": "string",
      "enum": ["simplelife", "lazyingart", "musia", "lalachan", "lalamv"],
      "description": "Publishing category: simplelife for personal/self daily recordings, lazyingart for LazyingArt brand/product/art posts, musia for pure song/audio-focused Musia content, lalachan for LALACHAN/Xiaoyunque fictional story videos, lalamv for LALACHAN character music videos/MVs"
    }
  },
  "required": [
    "title",
    "brief_description",
    "middle_description",
    "long_description",
    "tags",
    "english_words_to_learn",
    "teaser",
    "cover",
    "publish_category"
  ],
  "additionalProperties": false
}
